{
    "boxes": [
        [
            0.009000499732792377,
            -0.14948299527168274,
            0.1452299952507019,
            0.5715069770812988,
            1.0449700355529785,
            1.0473099946975708,
            0.0,
            1.0,
            0.0,
            0.0,
            0.0,
            1.0
        ],
        [
            -0.569923996925354,
            -0.005836999975144863,
            0.0015279999934136868,
            0.8587999939918518,
            1.3320399522781372,
            0.1803389936685562,
            0.0,
            1.0,
            0.0,
            0.0,
            0.0,
            1.0
        ],
        [
            -0.5708739757537842,
            -0.4476029872894287,
            0.5839890241622925,
            0.031560998409986496,
            0.16096000373363495,
            0.1716109961271286,
            0.0,
            1.0,
            0.0,
            0.0,
            0.0,
            1.0
        ],
        [
            -0.49197301268577576,
            -0.4476029872894287,
            -0.5016980171203613,
            0.031560998409986496,
            0.31876200437545776,
            0.3294140100479126,
            -0.0,
            1.0,
            0.0,
            0.0,
            0.0,
            1.0
        ],
        [
            0.021119499579072,
            0.3493039906024933,
            -0.17780600488185883,
            0.410288006067276,
            0.19029100239276886,
            1.0430099964141846,
            0.0,
            1.0,
            0.0,
            0.0,
            0.0,
            1.0
        ],
        [
            0.006562999915331602,
            -0.005836999975144863,
            -0.45887699723243713,
            0.8587999939918518,
            0.41123199462890625,
            1.018180012702942,
            0.0,
            1.0,
            0.0,
            0.0,
            0.0,
            1.0
        ]
    ],
    "ops": [
        [
            0,
            0,
            2,
            1,
            0,
            0,
            1,
            2,
            1,
            0,
            0,
            1,
            1
        ]
    ],
    "syms": [
        [
            0.0,
            1.0,
            -0.0,
            7.286680192919448e-05,
            0.006469499785453081,
            -0.005836999975144863,
            0.0015699999639764428,
            0.0
        ],
        [
            0.0,
            1.0,
            0.0,
            0.0,
            0.006093749776482582,
            -0.4476029872894287,
            0.5839890241622925,
            0.0
        ]
    ],
    "labels:": [
        [
            1,
            3,
            2,
            2,
            0,
            0
        ]
    ],
    "obj": 35809,
    "mat_index": 1188
}