{
    "boxes": [
        [
            0.0003209999995306134,
            -0.21091699600219727,
            0.13539500534534454,
            0.33443599939346313,
            0.8939520120620728,
            0.8939520120620728,
            0.0,
            1.0,
            0.0,
            0.0,
            0.0,
            1.0
        ],
        [
            -0.35910001397132874,
            -0.550574004650116,
            -0.21466200053691864,
            0.4215709865093231,
            0.1938380002975464,
            0.17510999739170074,
            0.0,
            1.0,
            0.0,
            0.0,
            0.0,
            1.0
        ],
        [
            -0.35913899540901184,
            -0.5506200194358826,
            0.49355998635292053,
            0.4214789867401123,
            0.1776220053434372,
            0.17503300309181213,
            0.0,
            1.0,
            0.0,
            0.0,
            0.0,
            1.0
        ],
        [
            0.0003209999995306134,
            0.4077169895172119,
            -0.20864300429821014,
            1.0513800382614136,
            0.2058749943971634,
            0.8939520120620728,
            0.0,
            1.0,
            0.0,
            0.0,
            0.0,
            1.0
        ]
    ],
    "ops": [
        [
            0,
            0,
            0,
            1,
            2,
            1,
            0,
            1
        ]
    ],
    "syms": [
        [
            0.0,
            0.9999920129776001,
            -0.0006917070131748915,
            -0.004030310083180666,
            -0.0005695000290870667,
            -0.5508220195770264,
            -0.21610699594020844,
            0.0
        ]
    ],
    "labels:": [
        [
            1,
            2,
            2,
            0
        ]
    ],
    "obj": 37148,
    "mat_index": 1939
}