{
    "boxes": [
        [
            -0.003215499920770526,
            -0.134675994515419,
            0.1537570059299469,
            0.09016700088977814,
            0.8181310296058655,
            0.8181310296058655,
            0.0,
            1.0,
            0.0,
            0.0,
            0.0,
            1.0
        ],
        [
            -0.3443709909915924,
            -0.44082799553871155,
            -0.1611579954624176,
            0.5626320242881775,
            0.1882999986410141,
            0.13176199793815613,
            0.0,
            1.0,
            0.0,
            0.0,
            0.0,
            1.0
        ],
        [
            0.3421570062637329,
            -0.4162600040435791,
            0.45344001054763794,
            0.6274930238723755,
            0.2187660038471222,
            0.13157199323177338,
            0.0,
            1.0,
            0.0,
            0.0,
            0.0,
            1.0
        ],
        [
            -0.0019069999689236283,
            0.37720099091529846,
            -0.20525899529457092,
            0.9621689915657043,
            0.10009899735450745,
            0.8145719766616821,
            0.0,
            1.0,
            0.0,
            0.0,
            0.0,
            1.0
        ]
    ],
    "ops": [
        [
            0,
            0,
            0,
            1,
            2,
            1,
            0,
            1
        ]
    ],
    "syms": [
        [
            0.0,
            0.9999920129776001,
            -0.003933669999241829,
            -0.00015623700164724141,
            -0.0019457499729469419,
            -0.4421750009059906,
            -0.1612119972705841,
            0.0
        ]
    ],
    "labels:": [
        [
            1,
            2,
            2,
            0
        ]
    ],
    "obj": 37807,
    "mat_index": 2323
}