{
    "boxes": [
        [
            -0.008248000405728817,
            0.06328249722719193,
            0.10205700248479843,
            0.13266900181770325,
            0.8344219923019409,
            0.6308479905128479,
            0.0,
            1.0,
            0.0,
            0.0,
            0.0,
            1.0
        ],
        [
            -0.26857098937034607,
            -0.3887360095977783,
            0.48014599084854126,
            0.8385509848594666,
            0.07824400067329407,
            0.11020199954509735,
            0.0,
            1.0,
            0.0,
            0.0,
            0.0,
            1.0
        ],
        [
            -0.2708840072154999,
            -0.39022600650787354,
            -0.272257000207901,
            0.8355709910392761,
            0.08579300343990326,
            0.10557600110769272,
            0.0,
            1.0,
            0.0,
            0.0,
            0.0,
            1.0
        ],
        [
            -0.11046899855136871,
            0.3873870074748993,
            -0.27653300762176514,
            0.3650600016117096,
            0.0771230012178421,
            0.05517299845814705,
            0.0,
            1.0,
            0.0,
            0.0,
            0.0,
            1.0
        ],
        [
            -0.04051699861884117,
            0.3861750066280365,
            -0.2763969898223877,
            0.36726999282836914,
            0.07750000059604645,
            0.06781399995088577,
            0.0,
            1.0,
            0.0,
            0.0,
            0.0,
            1.0
        ],
        [
            -0.008248499594628811,
            0.18544599413871765,
            -0.27447301149368286,
            0.1322299987077713,
            0.0813629999756813,
            0.6308469772338867,
            0.0,
            1.0,
            0.0,
            0.0,
            0.0,
            1.0
        ],
        [
            -0.23756200075149536,
            0.3841939866542816,
            -0.2763980031013489,
            0.3390519917011261,
            0.07751200348138809,
            0.17222000658512115,
            0.0,
            1.0,
            0.0,
            0.0,
            0.0,
            1.0
        ]
    ],
    "ops": [
        [
            0,
            0,
            0,
            1,
            2,
            1,
            0,
            0,
            1,
            2,
            0,
            2,
            0,
            2,
            1,
            1,
            1
        ]
    ],
    "syms": [
        [
            0.0,
            0.9998890161514282,
            0.013628499582409859,
            -0.006047530099749565,
            -0.007088500075042248,
            -0.3851720094680786,
            0.47856399416923523,
            0.0
        ],
        [
            0.0,
            0.9998329877853394,
            0.0182924997061491,
            8.159659773809835e-05,
            -0.009379249997437,
            0.3892360031604767,
            -0.27652499079704285,
            0.0
        ],
        [
            0.0,
            1.2346099538262933e-06,
            0.9999889731407166,
            -0.0047544799745082855,
            -0.008248250000178814,
            0.3879370093345642,
            -0.2754350006580353,
            0.0
        ],
        [
            0.0,
            0.9999819993972778,
            0.005995600018650293,
            0.0,
            -0.0077725001610815525,
            0.38557198643684387,
            -0.2763980031013489,
            0.0
        ]
    ],
    "labels:": [
        [
            1,
            2,
            2,
            0,
            0,
            0,
            0
        ]
    ],
    "obj": 38701,
    "mat_index": 2802
}