{
    "boxes": [
        [
            0.011730999685823917,
            -0.3329150080680847,
            0.2276419997215271,
            0.4890289902687073,
            1.0649900436401367,
            0.787962019443512,
            0.0,
            1.0,
            0.0,
            0.0,
            0.0,
            1.0
        ],
        [
            0.011727900244295597,
            0.3210330009460449,
            -0.26869499683380127,
            1.0081900358200073,
            0.3588609993457794,
            0.787975013256073,
            2.3159100237535313e-05,
            0.9604330062866211,
            -0.2785100042819977,
            3.082890179939568e-05,
            0.2785100042819977,
            0.9604330062866211
        ]
    ],
    "ops": [
        [
            0,
            0,
            1
        ]
    ],
    "syms": [
        [
            0.0,
            0.0,
            0.0,
            0.0,
            0.0,
            0.0,
            0.0,
            0.0
        ]
    ],
    "labels:": [
        [
            1,
            0
        ]
    ],
    "obj": 38813,
    "mat_index": 2865
}