{
    "boxes": [
        [
            0.020128000527620316,
            -0.11867299675941467,
            0.1106560006737709,
            0.4317280054092407,
            1.1591399908065796,
            1.078950047492981,
            0.0,
            1.0,
            0.0,
            0.0,
            0.0,
            1.0
        ],
        [
            -0.3381969928741455,
            -0.37826600670814514,
            -0.33049800992012024,
            0.32222700119018555,
            0.27682799100875854,
            0.36230000853538513,
            0.0,
            1.0,
            0.0,
            0.0,
            0.0,
            1.0
        ],
        [
            -0.33819499611854553,
            -0.3768390119075775,
            0.5593680143356323,
            0.3250789940357208,
            0.2617110013961792,
            0.3623049855232239,
            0.0,
            1.0,
            0.0,
            0.0,
            0.0,
            1.0
        ],
        [
            0.020128000527620316,
            0.43963199853897095,
            -0.3433789908885956,
            0.7714459896087646,
            0.25106701254844666,
            1.078950047492981,
            0.0,
            1.0,
            0.0,
            0.0,
            0.0,
            1.0
        ]
    ],
    "ops": [
        [
            0,
            0,
            0,
            1,
            2,
            1,
            0,
            1
        ]
    ],
    "syms": [
        [
            0.0,
            0.9997419714927673,
            0.02212969958782196,
            0.005047199781984091,
            0.023791799321770668,
            -0.3702529966831207,
            -0.3286699950695038,
            0.0
        ]
    ],
    "labels:": [
        [
            1,
            2,
            2,
            0
        ]
    ],
    "obj": 39294,
    "mat_index": 3135
}