{
    "boxes": [
        [
            0.009963500313460827,
            -0.148157998919487,
            0.1173510029911995,
            0.4546090066432953,
            1.1794699430465698,
            1.1981899738311768,
            0.0,
            1.0,
            0.0,
            0.0,
            0.0,
            1.0
        ],
        [
            -0.5253099799156189,
            0.145006000995636,
            0.15898700058460236,
            0.9498180150985718,
            1.0961999893188477,
            0.21176199615001678,
            0.0,
            1.0,
            0.0,
            0.0,
            0.0,
            1.0
        ],
        [
            -0.0016250000335276127,
            -0.41604098677635193,
            0.08297249674797058,
            0.11370900273323059,
            0.549107015132904,
            1.0538100004196167,
            0.0,
            1.0,
            0.0,
            0.0,
            0.0,
            1.0
        ],
        [
            0.009627999737858772,
            0.1458899974822998,
            -0.41846901178359985,
            0.981715977191925,
            0.1890989989042282,
            1.2816400527954102,
            0.0,
            1.0,
            0.0,
            0.0,
            0.0,
            1.0
        ]
    ],
    "ops": [
        [
            0,
            0,
            2,
            1,
            0,
            1,
            0,
            1
        ]
    ],
    "syms": [
        [
            0.0,
            0.999809980392456,
            -0.011395200155675411,
            0.0158246997743845,
            0.012400800362229347,
            0.1388770043849945,
            0.16749800741672516,
            0.0
        ]
    ],
    "labels:": [
        [
            1,
            3,
            2,
            0
        ]
    ],
    "obj": 39528,
    "mat_index": 3251
}