{
    "boxes": [
        [
            -0.002216000109910965,
            -0.00621700007468462,
            0.07736899703741074,
            0.24540400505065918,
            0.7162280082702637,
            0.7162280082702637,
            0.0,
            1.0,
            0.0,
            0.0,
            0.0,
            1.0
        ],
        [
            -0.29667899012565613,
            -0.4701330065727234,
            -0.21802100539207458,
            0.7754870057106018,
            0.12544800341129303,
            0.12730099260807037,
            0.0,
            1.0,
            0.0,
            0.0,
            0.0,
            1.0
        ],
        [
            -0.2805910110473633,
            -0.4671019911766052,
            0.34510600566864014,
            0.7815470099449158,
            0.18075299263000488,
            0.15947699546813965,
            0.0,
            1.0,
            0.0,
            0.0,
            0.0,
            1.0
        ],
        [
            -0.002216000109910965,
            0.5220810174942017,
            -0.19640499353408813,
            0.8711649775505066,
            0.16868099570274353,
            0.7162280082702637,
            0.0,
            1.0,
            0.0,
            0.0,
            0.0,
            1.0
        ]
    ],
    "ops": [
        [
            0,
            0,
            0,
            1,
            2,
            1,
            0,
            1
        ]
    ],
    "syms": [
        [
            0.0,
            0.9999690055847168,
            -0.0056508202105760574,
            -0.00547967990860343,
            -0.003058499889448285,
            -0.4717920124530792,
            -0.21963000297546387,
            0.0
        ]
    ],
    "labels:": [
        [
            1,
            2,
            2,
            0
        ]
    ],
    "obj": 40102,
    "mat_index": 3495
}