{
    "boxes": [
        [
            -0.014057500287890434,
            -0.1584099978208542,
            0.12046100199222565,
            0.4044409990310669,
            1.0016299486160278,
            0.8828129768371582,
            0.0,
            1.0,
            0.0,
            0.0,
            0.0,
            1.0
        ],
        [
            -0.42877501249313354,
            -0.06329350173473358,
            0.0493369996547699,
            0.7797210216522217,
            1.0472300052642822,
            0.10980699956417084,
            0.0,
            1.0,
            0.0,
            0.0,
            0.0,
            1.0
        ],
        [
            -0.4216969907283783,
            -0.5161100029945374,
            -0.32821398973464966,
            0.14253999292850494,
            0.17786000669002533,
            0.08446600288152695,
            0.0,
            1.0,
            0.0,
            0.0,
            0.0,
            1.0
        ],
        [
            -0.4216969907283783,
            -0.5161100029945374,
            0.4727109968662262,
            0.14253999292850494,
            0.13561999797821045,
            0.08446600288152695,
            0.0,
            1.0,
            0.0,
            0.0,
            0.0,
            1.0
        ],
        [
            -0.00788700021803379,
            0.4235230088233948,
            -0.30963799357414246,
            0.927232027053833,
            0.28586500883102417,
            0.7766159772872925,
            3.623150043874368e-11,
            0.9895550012588501,
            -0.14415499567985535,
            4.1892000285370656e-11,
            0.14415499567985535,
            0.9895550012588501
        ]
    ],
    "ops": [
        [
            0,
            0,
            2,
            1,
            0,
            0,
            1,
            2,
            1,
            0,
            1
        ]
    ],
    "syms": [
        [
            0.0,
            0.9994860291481018,
            -0.0,
            0.03205789998173714,
            0.0009127500234171748,
            -0.06329350173473358,
            0.06311900168657303,
            0.0
        ],
        [
            0.0,
            1.0,
            -0.0,
            -0.0,
            0.012906000018119812,
            -0.5161100029945374,
            -0.32821398973464966,
            0.0
        ]
    ],
    "labels:": [
        [
            1,
            3,
            2,
            2,
            0
        ]
    ],
    "obj": 42765,
    "mat_index": 4968
}