{
    "boxes": [
        [
            -0.008023999631404877,
            -0.34397000074386597,
            0.09125649929046631,
            0.25614801049232483,
            0.7362549901008606,
            0.9801999926567078,
            0.0,
            1.0,
            0.0,
            0.0,
            0.0,
            1.0
        ],
        [
            0.46741899847984314,
            -0.05060569941997528,
            0.17407700419425964,
            0.43093401193618774,
            0.5971519947052002,
            0.13760100305080414,
            0.22512799501419067,
            0.9742270112037659,
            -0.014114899560809135,
            0.0950779989361763,
            -0.0075487601570785046,
            0.9954410195350647
        ],
        [
            -0.46807000041007996,
            -0.6382049918174744,
            0.4287000000476837,
            0.3323209881782532,
            0.06136799976229668,
            0.06010900065302849,
            0.0,
            1.0,
            0.0,
            0.0,
            0.0,
            1.0
        ],
        [
            -0.46807000041007996,
            -0.6382049918174744,
            -0.04921500012278557,
            0.3323209881782532,
            0.06136799976229668,
            0.06010900065302849,
            0.0,
            1.0,
            0.0,
            0.0,
            0.0,
            1.0
        ],
        [
            -0.00845350045710802,
            0.2354390025138855,
            -0.19718599319458008,
            0.9848989844322205,
            0.3844749927520752,
            1.1205799579620361,
            0.0,
            1.0,
            0.0,
            0.0,
            0.0,
            1.0
        ]
    ],
    "ops": [
        [
            0,
            0,
            2,
            1,
            0,
            0,
            1,
            2,
            1,
            0,
            1
        ]
    ],
    "syms": [
        [
            0.0,
            0.9998779892921448,
            0.00011183600145159289,
            -0.01563039980828762,
            -0.0018088900251314044,
            -0.050658099353313446,
            0.1814119964838028,
            0.0
        ],
        [
            0.0,
            1.0,
            -0.0,
            -0.0,
            -0.008024250157177448,
            -0.6382049918174744,
            0.4287000000476837,
            0.0
        ]
    ],
    "labels:": [
        [
            1,
            3,
            2,
            2,
            0
        ]
    ],
    "obj": 42992,
    "mat_index": 5106
}