{
    "boxes": [
        [
            0.006312500219792128,
            -0.26349401473999023,
            0.10245999693870544,
            0.07573600113391876,
            0.7361019849777222,
            0.6107450127601624,
            0.0,
            1.0,
            0.0,
            0.0,
            0.0,
            1.0
        ],
        [
            -0.23046599328517914,
            -0.5743340253829956,
            -0.10682199895381927,
            0.5459449887275696,
            0.06439600139856339,
            0.07341299951076508,
            0.0,
            1.0,
            0.0,
            0.0,
            0.0,
            1.0
        ],
        [
            -0.23046599328517914,
            -0.574334979057312,
            0.43831300735473633,
            0.5459449887275696,
            0.06439600139856339,
            0.07341299951076508,
            -6.54520026921282e-17,
            1.0,
            -2.2204500197172533e-16,
            -6.54520026921282e-17,
            2.2204500197172533e-16,
            1.0
        ],
        [
            -0.009406499564647675,
            0.713172972202301,
            -0.14233000576496124,
            0.1790120005607605,
            0.28540098667144775,
            0.7087929844856262,
            0.0,
            1.0,
            0.0,
            0.0,
            0.0,
            1.0
        ],
        [
            -0.018897999078035355,
            0.19861599802970886,
            -0.17071600258350372,
            0.8484830260276794,
            0.06233600154519081,
            0.06233600154519081,
            0.0,
            1.0,
            0.0,
            0.0,
            0.0,
            1.0
        ],
        [
            -0.24405600130558014,
            0.19861599802970886,
            -0.10697200149297714,
            0.8484830260276794,
            0.06186499819159508,
            0.06186499819159508,
            0.0,
            1.0,
            0.0,
            0.0,
            0.0,
            1.0
        ],
        [
            -0.14104999601840973,
            0.19861599802970886,
            -0.16416600346565247,
            0.8484830260276794,
            0.06234300136566162,
            0.06234300136566162,
            0.0,
            1.0,
            0.0,
            0.0,
            0.0,
            1.0
        ]
    ],
    "ops": [
        [
            0,
            0,
            0,
            1,
            2,
            1,
            0,
            0,
            1,
            0,
            0,
            1,
            2,
            1,
            1
        ]
    ],
    "syms": [
        [
            0.0,
            1.0,
            -0.0,
            -0.0,
            0.0208382997661829,
            -0.5743340253829956,
            -0.10682199895381927,
            0.0
        ],
        [
            0.0,
            1.0,
            0.0,
            0.00018963799811899662,
            0.006421749945729971,
            0.19861599802970886,
            -0.10692500323057175,
            0.0
        ]
    ],
    "labels:": [
        [
            1,
            2,
            2,
            0,
            0,
            0,
            0
        ]
    ],
    "obj": 43033,
    "mat_index": 5138
}