{
    "boxes": [
        [
            -0.004228500183671713,
            -0.021593499928712845,
            0.12239400297403336,
            0.24652500450611115,
            0.9014719724655151,
            0.7446650266647339,
            0.0,
            1.0,
            0.0,
            0.0,
            0.0,
            1.0
        ],
        [
            -0.2947379946708679,
            -0.43862900137901306,
            -0.252934992313385,
            0.6298270225524902,
            0.1508139967918396,
            0.16364599764347076,
            0.0,
            1.0,
            0.0,
            0.0,
            0.0,
            1.0
        ],
        [
            -0.3101840019226074,
            -0.4369620084762573,
            0.5000590085983276,
            0.6331599950790405,
            0.14614200592041016,
            0.13275299966335297,
            0.0,
            1.0,
            0.0,
            0.0,
            0.0,
            1.0
        ],
        [
            -0.004228500183671713,
            0.4499030113220215,
            -0.24085000157356262,
            0.801967978477478,
            0.17498399317264557,
            0.7446650266647339,
            0.0,
            1.0,
            0.0,
            0.0,
            0.0,
            1.0
        ],
        [
            -0.08219549804925919,
            0.36397600173950195,
            -0.2408509999513626,
            0.6006060242652893,
            0.1749819964170456,
            0.09783700108528137,
            0.0,
            1.0,
            0.0,
            0.0,
            0.0,
            1.0
        ]
    ],
    "ops": [
        [
            0,
            0,
            0,
            1,
            2,
            1,
            0,
            0,
            2,
            1,
            1
        ]
    ],
    "syms": [
        [
            0.0,
            0.9999139904975891,
            0.0121155995875597,
            0.005053650122135878,
            0.00200224993750453,
            -0.43503299355506897,
            -0.2514350116252899,
            0.0
        ],
        [
            0.0,
            0.9998170137405396,
            -0.019152799621224403,
            2.2377400910045253e-06,
            0.029503699392080307,
            0.3618359863758087,
            -0.2408509999513626,
            0.0
        ]
    ],
    "labels:": [
        [
            1,
            2,
            2,
            0,
            0
        ]
    ],
    "obj": 43449,
    "mat_index": 5321
}