{
    "boxes": [
        [
            0.005249999929219484,
            -0.024112999439239502,
            0.1948709934949875,
            0.12333200126886368,
            0.5946289896965027,
            0.5961520075798035,
            0.0,
            1.0,
            0.0,
            0.0,
            0.0,
            1.0
        ],
        [
            0.005249999929219484,
            -0.41764599084854126,
            0.12226100265979767,
            0.8901000022888184,
            0.7582709789276123,
            0.5961520075798035,
            0.0,
            1.0,
            0.0,
            0.0,
            0.0,
            1.0
        ],
        [
            0.005248799920082092,
            0.4304890036582947,
            -0.14226600527763367,
            0.9869769811630249,
            0.09373170137405396,
            0.5962700247764587,
            -0.00012868299381807446,
            0.9955970048904419,
            -0.09373729676008224,
            -0.00014136800018604845,
            0.09373729676008224,
            0.9955970048904419
        ],
        [
            0.005249999929219484,
            0.4102970063686371,
            -0.23066399991512299,
            1.017680048942566,
            0.0524200014770031,
            0.5961520075798035,
            0.0,
            1.0,
            0.0,
            0.0,
            0.0,
            1.0
        ]
    ],
    "ops": [
        [
            0,
            0,
            1,
            0,
            0,
            1,
            1
        ]
    ],
    "syms": [
        [
            0.0,
            0.0,
            0.0,
            0.0,
            0.0,
            0.0,
            0.0,
            0.0
        ]
    ],
    "labels:": [
        [
            1,
            2,
            0,
            0
        ]
    ],
    "obj": 2876,
    "mat_index": 547
}