{
    "boxes": [
        [
            0.011312000453472137,
            0.03690899908542633,
            0.09757199883460999,
            0.24018999934196472,
            0.7505199909210205,
            0.7190380096435547,
            0.0,
            1.0,
            0.0,
            0.0,
            0.0,
            1.0
        ],
        [
            0.013643000274896622,
            -0.29595300555229187,
            0.03035550005733967,
            0.6887930035591125,
            0.8849530220031738,
            0.7712600231170654,
            0.0,
            1.0,
            0.0,
            0.0,
            0.0,
            1.0
        ],
        [
            0.0074561298824846745,
            0.5314239859580994,
            -0.259086012840271,
            0.7990819811820984,
            0.1611109972000122,
            0.5886520147323608,
            -0.018152400851249695,
            0.9893879890441895,
            -0.14416199922561646,
            -0.02098499983549118,
            0.143776997923851,
            0.9893879890441895
        ]
    ],
    "ops": [
        [
            0,
            0,
            1,
            0,
            1
        ]
    ],
    "syms": [
        [
            0.0,
            0.0,
            0.0,
            0.0,
            0.0,
            0.0,
            0.0,
            0.0
        ]
    ],
    "labels:": [
        [
            1,
            2,
            0
        ]
    ],
    "obj": 44742,
    "mat_index": 5893
}