{
    "boxes": [
        [
            -0.001411000033840537,
            -0.11225900053977966,
            0.09399200230836868,
            0.2657270133495331,
            1.0050100088119507,
            0.8190339803695679,
            0.0,
            1.0,
            0.0,
            0.0,
            0.0,
            1.0
        ],
        [
            -0.3339749872684479,
            -0.5210409760475159,
            -0.20566800236701965,
            0.551934003829956,
            0.14844299852848053,
            0.14844200015068054,
            0.0,
            1.0,
            0.0,
            0.0,
            0.0,
            1.0
        ],
        [
            -0.3323670029640198,
            -0.5183200240135193,
            0.5195090174674988,
            0.551934003829956,
            0.14844299852848053,
            0.14844299852848053,
            -0.0,
            1.0,
            -2.2204500197172533e-16,
            0.0,
            2.2204500197172533e-16,
            1.0
        ],
        [
            -0.3053480088710785,
            0.31040599942207336,
            -0.1908770054578781,
            0.7387229800224304,
            0.11558999866247177,
            0.10959000140428543,
            0.0,
            1.0,
            0.0,
            0.0,
            0.0,
            1.0
        ],
        [
            -0.15853500366210938,
            0.3173789978027344,
            -0.2739669978618622,
            0.7389829754829407,
            0.09147299826145172,
            0.10152599960565567,
            0.0,
            1.0,
            0.0,
            0.0,
            0.0,
            1.0
        ],
        [
            -0.0015529999509453773,
            0.7108539938926697,
            -0.23027099668979645,
            0.1550469994544983,
            0.2721799910068512,
            0.8040879964828491,
            0.0,
            1.0,
            0.0,
            0.0,
            0.0,
            1.0
        ],
        [
            -0.0256935004144907,
            0.3113349974155426,
            -0.29175999760627747,
            0.7330219745635986,
            0.10081800073385239,
            0.10130299627780914,
            0.0,
            1.0,
            0.0,
            0.0,
            0.0,
            1.0
        ]
    ],
    "ops": [
        [
            0,
            0,
            0,
            1,
            2,
            1,
            0,
            0,
            1,
            2,
            0,
            0,
            2,
            1,
            1,
            1
        ]
    ],
    "syms": [
        [
            0.0,
            0.9999790191650391,
            0.004077599849551916,
            -0.005050919950008392,
            -0.00033000000985339284,
            -0.5196800231933594,
            -0.20735299587249756,
            0.0
        ],
        [
            0.0,
            0.9997259974479675,
            0.01465780008584261,
            0.018224600702524185,
            -0.006053609773516655,
            0.31479400396347046,
            -0.18542100489139557,
            0.0
        ],
        [
            0.0,
            0.9979439973831177,
            0.042445600032806396,
            0.04801949858665466,
            0.03535899892449379,
            0.31393200159072876,
            -0.2888219952583313,
            0.0
        ]
    ],
    "labels:": [
        [
            1,
            2,
            2,
            0,
            0,
            0,
            0
        ]
    ],
    "obj": 45035,
    "mat_index": 5995
}