{
    "boxes": [
        [
            0.0035059999208897352,
            -0.18197199702262878,
            -0.00235849991440773,
            0.6330659985542297,
            1.1193599700927734,
            1.2286800146102905,
            0.0,
            1.0,
            0.0,
            0.0,
            0.0,
            1.0
        ],
        [
            -0.5197020173072815,
            0.30270901322364807,
            0.19052499532699585,
            0.49167999625205994,
            0.7335919737815857,
            0.36540400981903076,
            0.0,
            1.0,
            0.0,
            0.0,
            0.0,
            1.0
        ],
        [
            -0.4963020086288452,
            -0.5355839729309082,
            0.43962299823760986,
            0.08411400020122528,
            0.13065800070762634,
            0.1400739997625351,
            0.0,
            1.0,
            0.0,
            0.0,
            0.0,
            1.0
        ],
        [
            -0.37905699014663696,
            -0.5355839729309082,
            -0.3007580041885376,
            0.08411400020122528,
            0.13065700232982635,
            0.1400730013847351,
            0.0,
            1.0,
            0.0,
            0.0,
            0.0,
            1.0
        ],
        [
            0.014682999812066555,
            0.2720380127429962,
            -0.3316580057144165,
            0.5543299913406372,
            0.6335740089416504,
            1.374559998512268,
            0.0,
            1.0,
            0.0,
            0.0,
            0.0,
            1.0
        ]
    ],
    "ops": [
        [
            0,
            0,
            2,
            1,
            0,
            0,
            1,
            2,
            1,
            0,
            1
        ]
    ],
    "syms": [
        [
            0.0,
            0.9984890222549438,
            0.01467679999768734,
            0.0529555007815361,
            0.010366500355303288,
            0.31050100922584534,
            0.21863700449466705,
            0.0
        ],
        [
            0.0,
            1.0,
            -0.0,
            -0.0,
            0.0033340000081807375,
            -0.5355839729309082,
            0.43962299823760986,
            0.0
        ]
    ],
    "labels:": [
        [
            1,
            3,
            2,
            2,
            0
        ]
    ],
    "obj": 3064,
    "mat_index": 638
}