{
    "boxes": [
        [
            0.005497000180184841,
            0.06023599952459335,
            0.07924950122833252,
            0.1001800000667572,
            0.6361470222473145,
            0.5597140192985535,
            0.0,
            1.0,
            0.0,
            0.0,
            0.0,
            1.0
        ],
        [
            0.2735779881477356,
            -0.4393889904022217,
            -0.2213200032711029,
            0.9559310078620911,
            0.032055001705884933,
            0.019370999187231064,
            0.0,
            1.0,
            0.0,
            0.0,
            0.0,
            1.0
        ],
        [
            0.005601999815553427,
            -0.43410199880599976,
            -0.2213200032711029,
            0.0328029990196228,
            0.032055001705884933,
            0.5046979784965515,
            0.0,
            1.0,
            0.0,
            0.0,
            0.0,
            1.0
        ],
        [
            -0.2523910105228424,
            -0.4441309869289398,
            0.3733699917793274,
            0.9493579864501953,
            0.04790699854493141,
            0.04312499985098839,
            0.0,
            1.0,
            0.0,
            0.0,
            0.0,
            1.0
        ],
        [
            -0.2562980055809021,
            -0.43198299407958984,
            -0.22132399678230286,
            0.9709960222244263,
            0.034637000411748886,
            0.03339499980211258,
            0.0,
            1.0,
            0.0,
            0.0,
            0.0,
            1.0
        ],
        [
            -0.25950801372528076,
            -0.43267300724983215,
            0.07856850326061249,
            0.0328029990196228,
            0.5945829749107361,
            0.02552199922502041,
            0.0,
            1.0,
            0.0,
            0.0,
            0.0,
            1.0
        ],
        [
            0.0054576401598751545,
            0.2801940143108368,
            -0.20066100358963013,
            0.5014849901199341,
            0.10246799886226654,
            0.5596150159835815,
            -0.00019361800514161587,
            0.9994609951972961,
            -0.03281269967556,
            -0.00020007899729534984,
            0.03281269967556,
            0.9994609951972961
        ]
    ],
    "ops": [
        [
            0,
            0,
            0,
            2,
            1,
            0,
            2,
            0,
            0,
            2,
            1,
            1,
            1,
            1,
            0,
            1
        ]
    ],
    "syms": [
        [
            0.0,
            0.004894750192761421,
            0.002353040035814047,
            0.9999849796295166,
            0.0070872497744858265,
            -0.43338799476623535,
            0.08211330324411392,
            0.0
        ],
        [
            0.0,
            0.9998810291290283,
            0.008853539824485779,
            0.012644999660551548,
            0.008688749745488167,
            -0.4418190121650696,
            0.3766709864139557,
            0.0
        ],
        [
            0.0,
            1.0,
            -0.0,
            -0.0,
            0.006291999947279692,
            -0.43267300724983215,
            0.07856850326061249,
            0.0
        ]
    ],
    "labels:": [
        [
            1,
            2,
            2,
            2,
            2,
            2,
            0
        ]
    ],
    "obj": 3196,
    "mat_index": 709
}