{
    "boxes": [
        [
            -0.0021689999848604202,
            -0.3341909945011139,
            0.15101300179958344,
            0.7420650124549866,
            1.5572099685668945,
            1.5809400081634521,
            0.0,
            1.0,
            0.0,
            0.0,
            0.0,
            1.0
        ],
        [
            -0.0021879998967051506,
            0.18776699900627136,
            -0.21397900581359863,
            0.9024689793586731,
            0.859341025352478,
            1.580899953842163,
            0.0,
            1.0,
            0.0,
            0.0,
            0.0,
            1.0
        ]
    ],
    "ops": [
        [
            0,
            0,
            1
        ]
    ],
    "syms": [
        [
            0.0,
            0.0,
            0.0,
            0.0,
            0.0,
            0.0,
            0.0,
            0.0
        ]
    ],
    "labels:": [
        [
            1,
            0
        ]
    ],
    "obj": 44270,
    "mat_index": 5736,
    "obbs": "N 2\n-0.002188 0.187767 -0.213979 1 0 0 0 1 0 0 0 1 1.5809 0.902469 0.859341\n-0.002169 -0.334191 0.151013 1 0 0 0 1 0 0 0 1 1.58094 0.742065 1.55721\nC 1\n0 1\nS 0\nL 2\n0\n1"
}